
        <logs xmlns="http://www.witsml.org/schemas/1series" version="1.4.1.1">
            <log>
                <name>RealTime_Drilling</name>
                <logCurveInfo><mnemonic>TIME</mnemonic></logCurveInfo>
                <logCurveInfo><mnemonic>DEPT</mnemonic></logCurveInfo>
                <logCurveInfo><mnemonic>HKLD</mnemonic></logCurveInfo>
                <logCurveInfo><mnemonic>WOB</mnemonic></logCurveInfo>
                <logCurveInfo><mnemonic>ROP</mnemonic></logCurveInfo>
                <logCurveInfo><mnemonic>RPM</mnemonic></logCurveInfo>
                <logCurveInfo><mnemonic>SPP</mnemonic></logCurveInfo>
                
                <logData>
                    <data>2026-02-22T16:27:19.188495,1053.00,201.17,13.91,31.14,122.27,3049.88</data>
                </logData>
            </log>
        </logs>
        