
        <logs xmlns="http://www.witsml.org/schemas/1series" version="1.4.1.1">
            <log>
                <name>RealTime_Drilling</name>
                <logCurveInfo><mnemonic>TIME</mnemonic></logCurveInfo>
                <logCurveInfo><mnemonic>DEPT</mnemonic></logCurveInfo>
                <logCurveInfo><mnemonic>HKLD</mnemonic></logCurveInfo>
                <logCurveInfo><mnemonic>WOB</mnemonic></logCurveInfo>
                <logCurveInfo><mnemonic>ROP</mnemonic></logCurveInfo>
                <logCurveInfo><mnemonic>RPM</mnemonic></logCurveInfo>
                <logCurveInfo><mnemonic>SPP</mnemonic></logCurveInfo>
                
                <logData>
                    <data>2026-02-16T09:14:06.092409,1148.00,204.54,14.76,34.09,121.18,2951.35</data>
                </logData>
            </log>
        </logs>
        