
        <logs xmlns="http://www.witsml.org/schemas/1series" version="1.4.1.1">
            <log>
                <name>RealTime_Drilling</name>
                <logCurveInfo><mnemonic>TIME</mnemonic></logCurveInfo>
                <logCurveInfo><mnemonic>DEPT</mnemonic></logCurveInfo>
                <logCurveInfo><mnemonic>HKLD</mnemonic></logCurveInfo>
                <logCurveInfo><mnemonic>WOB</mnemonic></logCurveInfo>
                <logCurveInfo><mnemonic>ROP</mnemonic></logCurveInfo>
                <logCurveInfo><mnemonic>RPM</mnemonic></logCurveInfo>
                <logCurveInfo><mnemonic>SPP</mnemonic></logCurveInfo>
                
                <logData>
                    <data>2026-02-22T16:17:11.013399,1123.50,201.61,13.89,45.43,116.53,2999.45</data>
                </logData>
            </log>
        </logs>
        