
        <logs xmlns="http://www.witsml.org/schemas/1series" version="1.4.1.1">
            <log>
                <name>RealTime_Drilling</name>
                <logCurveInfo><mnemonic>TIME</mnemonic></logCurveInfo>
                <logCurveInfo><mnemonic>DEPT</mnemonic></logCurveInfo>
                <logCurveInfo><mnemonic>HKLD</mnemonic></logCurveInfo>
                <logCurveInfo><mnemonic>WOB</mnemonic></logCurveInfo>
                <logCurveInfo><mnemonic>ROP</mnemonic></logCurveInfo>
                <logCurveInfo><mnemonic>RPM</mnemonic></logCurveInfo>
                <logCurveInfo><mnemonic>SPP</mnemonic></logCurveInfo>
                
                <logData>
                    <data>2026-02-17T12:18:26.010676,1614.50,198.18,14.75,47.11,116.74,3000.35</data>
                </logData>
            </log>
        </logs>
        