
        <logs xmlns="http://www.witsml.org/schemas/1series" version="1.4.1.1">
            <log>
                <name>RealTime_Drilling</name>
                <logCurveInfo><mnemonic>TIME</mnemonic></logCurveInfo>
                <logCurveInfo><mnemonic>DEPT</mnemonic></logCurveInfo>
                <logCurveInfo><mnemonic>HKLD</mnemonic></logCurveInfo>
                <logCurveInfo><mnemonic>WOB</mnemonic></logCurveInfo>
                <logCurveInfo><mnemonic>ROP</mnemonic></logCurveInfo>
                <logCurveInfo><mnemonic>RPM</mnemonic></logCurveInfo>
                <logCurveInfo><mnemonic>SPP</mnemonic></logCurveInfo>
                
                <logData>
                    <data>2026-02-22T16:23:02.994630,1207.50,199.20,15.70,40.38,122.85,3010.13</data>
                </logData>
            </log>
        </logs>
        